quizpy/__init__.py
quizpy/common.py
quizpy/drag.py
quizpy/multipe_choice.py
quizpy/numerical.py
quizpy/text.py
quizpy-0.0.4.dist-info/LICENSE
quizpy-0.0.4.dist-info/METADATA
quizpy-0.0.4.dist-info/WHEEL
quizpy-0.0.4.dist-info/top_level.txt
quizpy-0.0.4.dist-info/RECORD
