Metadata-Version: 2.1
Name: quizpy
Version: 0.0.4
Summary: A package to create Moodle exams using Python
Home-page: https://git.tu-berlin.de/tkn/quizpy
Author: Sebastian Bräuer
Author-email: braeuer@tu-berlin.de
License: UNKNOWN
Platform: UNKNOWN
Classifier: Programming Language :: Python :: 3
Classifier: License :: OSI Approved :: GNU General Public License v3 or later (GPLv3+)
Classifier: Operating System :: OS Independent
Requires-Python: >=3.6
License-File: LICENSE
